TOPSIS_Anmoldeep_101983056.py
TOPSIS_Anmoldeep_101983056-0.2.dist-info/LICENSE.txt
TOPSIS_Anmoldeep_101983056-0.2.dist-info/METADATA
TOPSIS_Anmoldeep_101983056-0.2.dist-info/WHEEL
TOPSIS_Anmoldeep_101983056-0.2.dist-info/top_level.txt
TOPSIS_Anmoldeep_101983056-0.2.dist-info/RECORD
