Metadata-Version: 2.1
Name: TOPSIS-Anmoldeep-101983056
Version: 0.2
Summary: Package for Multiple-criteria decision-making using TOPSIS.
Home-page: https://github.com/anmoldeep7/TOPSIS_AnmoldeepSingh_101983056-
Author: Anmoldeep Singh
Author-email: mitultandon56@gmail.com
License: MIT
Download-URL: https://github.com/anmoldeep7/TOPSIS_AnmoldeepSingh_101983056-/archive/v_01.tar.gz
Keywords: TOPSIS,MCDA,DS
Platform: UNKNOWN
Classifier: Development Status :: 3 - Alpha
Classifier: Intended Audience :: Developers
Classifier: Topic :: Software Development :: Build Tools
Classifier: License :: OSI Approved :: MIT License
Classifier: Programming Language :: Python :: 3
Classifier: Programming Language :: Python :: 3.4
Classifier: Programming Language :: Python :: 3.5
Classifier: Programming Language :: Python :: 3.6
Requires-Dist: pandas
Requires-Dist: numpy
